YongPythonHePygameXieYouxiCongRumenDaoJingtong/README.md
YongPythonHePygameXieYouxiCongRumenDaoJingtong/__init__.py
YongPythonHePygameXieYouxiCongRumenDaoJingtong/__main__.py
YongPythonHePygameXieYouxiCongRumenDaoJingtong/file.pdf
YongPythonHePygameXieYouxiCongRumenDaoJingtong/index.html
yong_python_he_pygame_xie_youxi_cong_rumen_dao_jingtong-2024.2.29.0.dist-info/METADATA
yong_python_he_pygame_xie_youxi_cong_rumen_dao_jingtong-2024.2.29.0.dist-info/WHEEL
yong_python_he_pygame_xie_youxi_cong_rumen_dao_jingtong-2024.2.29.0.dist-info/entry_points.txt
yong_python_he_pygame_xie_youxi_cong_rumen_dao_jingtong-2024.2.29.0.dist-info/top_level.txt
yong_python_he_pygame_xie_youxi_cong_rumen_dao_jingtong-2024.2.29.0.dist-info/RECORD
